{
  "id": "俚语歇后语故事系列-俚语故事01-竹篮打水-一场空",
  "title": "俚语故事01：《竹篮打水——一场空》",
  "emoji": "💬",
  "series": "俚语歇后语故事系列",
  "series_category": "language",
  "desc": "雷迪嘎嘎系列俚语歇后语故事系列中的故事",
  "pages": 16,
  "age": "5-10岁",
  "time": 6,
  "status": "即将上线",
  "chars": [
    "噶丫丫",
    "噶巴巴",
    "雷迪嘎嘎"
  ],
  "tags": [
    "趣味",
    "歇后语",
    "俚语"
  ],
  "text": [
    {
      "page": 1,
      "body": "清晨，乌鸦森林里阳光明媚。雷迪嘎嘎带着噶巴巴和噶丫丫在湖边散步。"
    },
    {
      "page": 2,
      "body": "\"嘎嘎嘎，今天天气真好啊！\"噶巴巴开心地扇动着小翅膀。"
    },
    {
      "page": 3,
      "body": "湖面上漂浮着许多闪亮的小东西。噶丫丫好奇地问：\"那是什么呀？\""
    },
    {
      "page": 4,
      "body": "雷迪嘎嘎推了推眼镜：\"那是水面的倒影在阳光下的光斑，看起来美丽但不真实。\""
    },
    {
      "page": 5,
      "body": "噶巴巴看到水面，兴奋地说：\"我去把水装满带回家喝！\""
    },
    {
      "page": 6,
      "body": "他找来一个竹子编的篮子，认认真真地往里面舀水。"
    },
    {
      "page": 7,
      "body": "舀了满满一篮子水，噶巴巴小心翼翼地捧着往回走。"
    },
    {
      "page": 8,
      "body": "可是水滴却从竹篮的缝隙里一滴一滴地漏了出来。"
    },
    {
      "page": 9,
      "body": "\"哎呀！怎么一直在漏水？\"噶巴巴着急地加快脚步。"
    },
    {
      "page": 10,
      "body": "水越漏越多，还没走到家，篮子里已经一滴水都不剩了。"
    },
    {
      "page": 11,
      "body": "噶巴巴垂头丧气地回来了：\"爸爸，水全漏光了！\""
    },
    {
      "page": 12,
      "body": "雷迪嘎嘎慈祥地笑了：\"嘎嘎嘎，用竹篮打水，就是白费力气，什么也得不到。\""
    },
    {
      "page": 13,
      "body": "\"'竹篮打水——一场空'，这个歇后语就是比喻费了很大力气，结果什么也没得到。\""
    },
    {
      "page": 14,
      "body": "噶丫丫点点头：\"就像我做梦梦到好多好吃的，醒来却什么都没有！\""
    },
    {
      "page": 15,
      "body": "雷迪嘎嘎说：\"所以小朋友们做事要选对方法，不然就会竹篮打水——一场空哦。\""
    },
    {
      "page": 16,
      "body": "三个小伙伴开心地在森林里继续散步，学习新的知识。\n---\n*故事完*"
    }
  ],
  "source": "俚语歇后语故事系列/故事文本/俚语_001_竹篮打水.md"
}