{
  "id": "俚语歇后语故事系列-歇后语故事030-板上钉钉-跑不了",
  "title": "歇后语故事030：《板上钉钉——跑不了》",
  "emoji": "💬",
  "series": "俚语歇后语故事系列",
  "series_category": "language",
  "desc": "雷迪嘎嘎系列俚语歇后语故事系列中的故事",
  "pages": 15,
  "age": "5-10岁",
  "time": 6,
  "status": "即将上线",
  "chars": [
    "噶丫丫",
    "噶巴巴",
    "雷迪嘎嘎"
  ],
  "tags": [
    "趣味",
    "歇后语",
    "俚语"
  ],
  "text": [
    {
      "page": 1,
      "body": "小鸭子波波向小鸡承诺：\"我明天一定借你三颗种子！\""
    },
    {
      "page": 2,
      "body": "小鸡说：\"太好了，你说话要算数哦！\""
    },
    {
      "page": 3,
      "body": "可是第二天，小鸭子波波却忘了这件事。"
    },
    {
      "page": 4,
      "body": "第三天小鸡来找波波，波波说：\"哎呀，我忘了...\""
    },
    {
      "page": 5,
      "body": "雷迪嘎嘎知道了这件事。"
    },
    {
      "page": 6,
      "body": "爸爸拿出一个木板和一颗钉子示范。"
    },
    {
      "page": 7,
      "body": "\"你们看，钉子钉进木板里，就跑不了了。\"爸爸说。"
    },
    {
      "page": 8,
      "body": "\"这就叫'板上钉钉——跑不了'。\""
    },
    {
      "page": 9,
      "body": "\"意思是说过的话、答应的事，就像钉在木板上的钉子一样，不能反悔了。\""
    },
    {
      "page": 10,
      "body": "小鸭子波波听了，脸红了：\"对不起，我明天一定把种子给你！\""
    },
    {
      "page": 11,
      "body": "第四天，波波真的把三颗种子给了小鸡。"
    },
    {
      "page": 12,
      "body": "小鸡高兴地说：\"谢谢你，你真是一个守信用的小鸭子！\""
    },
    {
      "page": 13,
      "body": "爸爸说：\"答应别人的事就要做到，这样大家才会信任你。\""
    },
    {
      "page": 14,
      "body": "噶巴巴和噶丫丫都记住了：说过的话，就像板上钉钉，跑不了！"
    },
    {
      "page": 15,
      "body": "森林里又恢复了平静，大家都学会了守信用。\n---\n*故事完*"
    }
  ],
  "source": "俚语歇后语故事系列/故事文本/俚语_030_板上钉钉.md"
}