{
  "id": "噶丫丫领养故事-噶丫丫领养故事006-夜晚的恐惧",
  "title": "噶丫丫领养故事006：《夜晚的恐惧》",
  "emoji": "📖",
  "series": "噶丫丫领养故事",
  "series_category": "growth",
  "desc": "第一次在树洞里过夜，噶丫丫害怕黑暗，爸爸和哥哥用爱驱散了她的恐惧。",
  "pages": 6,
  "age": "3-8岁",
  "time": 6,
  "status": "即将上线",
  "chars": [
    "噶丫丫",
    "噶巴巴",
    "雷迪嘎嘎"
  ],
  "tags": [
    "领养",
    "家庭",
    "寓意"
  ],
  "text": [
    {
      "page": 1,
      "body": "天黑了，树洞里变得很暗。\n###"
    },
    {
      "page": 2,
      "body": "\"呜……\"噶丫丫小声哭了起来。\n###"
    },
    {
      "page": 3,
      "body": "\"妹妹，怎么了？\"噶巴巴赶紧飞过去。\n### 第四页\n\"好黑……我害怕……\"噶丫丫抱着羽毛床发抖。\n###"
    },
    {
      "page": 5,
      "body": "爸爸点燃了一根小树枝，树洞里亮了起来。\n### 第六页\n\"别怕，\"爸爸说，\"这只是夜晚而已。\"\n###"
    },
    {
      "page": 7,
      "body": "\"可是……可是黑暗里有怪物……\"噶丫丫说。\n### 第八页\n\"没有怪物的，\"噶巴巴说，\"我小时候也怕黑，后来爸爸教了我一个办法。\"\n###"
    },
    {
      "page": 9,
      "body": "\"什么办法？\"噶丫丫好奇地问。\n### 第十页\n噶巴巴说：\"爸爸告诉我，闭上眼睛想象美好的事情。\"\n### 第十一页\n\"我想象和爸爸一起飞，和妹妹一起玩……\"噶巴巴说，\"想着想着就不怕了。\"\n### 第十二页\n爸爸笑了：\"这个办法很有效。\"\n### 第十三页\n\"我试试，\"噶丫丫闭上眼睛。\n### 第十四页\n\"我想象……爸爸抱着我，哥哥给我讲故事……\"\n### 第十五页\n\"还有我们在森林里一起找浆果……\"\n### 第十六页\n慢慢地，噶丫丫的脸上露出了微笑。\n### 第十七页\n\"我不怕了，\"她说，\"因为我知道爸爸和哥哥在身边。\"\n### 第十八页\n爸爸轻轻拍着她的背：\"睡吧，孩子，爸爸妈妈……爸爸和哥哥会保护你的。\"\n### 第十九页\n\"晚安，爸爸。晚安，哥哥。\"噶丫丫睡着了。\n### 第二十页\n那一夜，她睡得很安稳。\n---\n## 故事寓意\n爱是最温暖的灯，它能驱散所有的恐惧。\n## 主题\n克服恐惧、爱与陪伴"
    }
  ],
  "source": "噶丫丫领养故事/故事文本/噶丫丫领养_006_夜晚的恐惧.md"
}