{
  "id": "噶巴巴成长系列-噶巴巴成长故事044-迈出第一步",
  "title": "噶巴巴成长故事044：迈出第一步",
  "emoji": "⭐",
  "series": "噶巴巴成长系列",
  "series_category": "growth",
  "desc": "雷迪嘎嘎系列噶巴巴成长系列中的故事",
  "pages": 6,
  "age": "3-6岁",
  "time": 5,
  "status": "即将上线",
  "chars": [
    "噶巴巴"
  ],
  "tags": [
    "勇气",
    "成长"
  ],
  "text": [
    {
      "page": 1,
      "body": "学校要举办运动会的消息传开了。\n噶巴巴很兴奋，可是看到比赛项目后，他的心又凉了。\n##"
    },
    {
      "page": 2,
      "body": "有跑步、跳远、游泳……还有一项他从来没尝试过的——攀岩。\n“天哪，攀岩好可怕呀！”他想。\n##"
    },
    {
      "page": 3,
      "body": "噶巴巴从来不敢尝试新运动。\n他觉得自己做不好，会摔下来，会被同学笑话。\n## 第四页\n体育课上，老师说：“这次运动会，大家可以报名参加任何项目。”\n“勇于尝试的精神比成绩更重要。”\n##"
    },
    {
      "page": 5,
      "body": "可是噶巴巴还是不敢报名。\n他选了大家都熟悉的跑步，没有选攀岩。\n## 第六页\n运动会那天，噶巴巴去看攀岩比赛。\n看着同学们一步步往上爬，他既羡慕又害怕。\n##"
    },
    {
      "page": 7,
      "body": "“哇，好厉害呀！”观众们为攀岩的同学鼓掌。\n噶巴巴想：“要是我也能爬上去就好了……”\n## 第八页\n回到家，他跟爸爸说了这件事。\n“其实我也想试试攀岩，可是我不敢……”\n##"
    },
    {
      "page": 9,
      "body": "爸爸问：“你害怕什么呢？是怕摔下来，还是怕做得不好？”\n噶巴巴想了想：“我怕……怕自己爬不上去，太丢人了。”\n## 第十页\n爸爸笑着说：“还没试过就怕丢人，这才是真正的丢人呀。”\n“爸爸以前也不敢尝试新东西，后来发现其实没那么可怕。”\n## 第十一页\n爸爸给他讲了一个故事：\n“一只小乌鸦看到蝴蝶在花丛中飞舞，很羡慕。”\n## 第十二页\n“小乌鸦也想学飞，可是他怕飞不高、飞不稳。”\n“后来在妈妈的鼓励下，他试着扇动翅膀，没想到真的飞起来了！”\n## 第十三页\n爸爸说：“很多事情，你不去试，永远不知道自己做不做得到。”\n“而且，就算第一次失败了也没关系，失败是成功之母呀。”\n## 第十四页\n噶巴巴问：“那我该怎么克服害怕呢？”\n爸爸教他几个方法：\n## 第十五页\n“第一，做好准备。”爸爸说。\n“了解这个运动是什么，注意什么，做好安全措施。”\n## 第十六页\n“第二，从简单的开始。”爸爸继续说。\n“不要一上来就做最难的，从基础开始，慢慢进步。”\n## 第十七页\n“第三，告诉自己'我可以'。”爸爸补充道。\n“积极的心理暗示能给你勇气和力量。”\n## 第十八页\n“第四，找人陪伴。”爸爸说。\n“有教练或者朋友在旁边，你会更安心。”\n## 第十九页\n过了一段时间，学校又有新的体验活动——攀岩体验课。\n噶巴巴这次鼓起勇气报了名。\n## 第二十页\n站在攀岩墙下，他的心砰砰直跳。\n可是他深吸一口气，想起了爸爸的话：“我可以的！”\n## 第二十一页\n他一步步往上爬，中间有几次差点滑下来。\n但是他没有放弃，继续努力往上。\n## 第二十二页\n终于，噶巴巴爬到了顶端！\n“哇——”观众们为他鼓掌，噶巴巴的心里美滋滋的。\n## 第二十三页\n下来之后，他发现其实没有想象中那么可怕。\n“原来我也可以做到呀！”他兴奋地说。\n## 第二十四页\n从那以后，噶巴巴不再害怕尝试新运动了。\n他还学会了轮滑、羽毛球，生活变得更多彩了。\n## 第二十五页\n【成长感悟】\n害怕是正常的，但不要让害怕阻止你前进。\n勇敢迈出第一步，你会发现很多事没有想象中那么难！"
    }
  ],
  "source": "噶巴巴成长系列/故事文本/噶巴巴成长_044_不敢尝试新运动.md"
}