{
  "id": "诗歌故事系列-南歌子-香墨弯弯画-秦观",
  "title": "《南歌子·香墨弯弯画》- 秦观",
  "emoji": "🎭",
  "series": "诗歌故事系列",
  "series_category": "poetry",
  "desc": "雷迪嘎嘎系列诗歌故事系列中的故事",
  "pages": 6,
  "age": "3-8岁",
  "time": 6,
  "status": "即将上线",
  "chars": [
    "雷迪嘎嘎"
  ],
  "tags": [
    "诗歌",
    "韵律"
  ],
  "text": [
    {
      "page": 1,
      "body": "雷迪嘎嘎给孩子们念词。"
    },
    {
      "page": 2,
      "body": "\"'香墨弯弯画，燕脂淡淡匀'。\""
    },
    {
      "page": 3,
      "body": "\"'香墨弯弯画，燕脂淡淡匀。'\""
    },
    {
      "page": 4,
      "body": "爸爸说：\"这是秦观写的《南歌子》。\""
    },
    {
      "page": 5,
      "body": "\"'揉蓝衫子杏黄裙，独倚玉阑无语点檀唇'。\""
    },
    {
      "page": 6,
      "body": "\"'揉蓝衫子杏黄裙，独倚玉阑无语点檀唇。'\"\n---\n*故事完*"
    }
  ],
  "source": "诗歌故事系列/故事文本/诗歌_190_南歌子香墨弯弯画.md"
}