{
  "id": "诗歌故事系列-柳营曲-范蠡-曾瑞",
  "title": "《柳营曲·范蠡》- 曾瑞",
  "emoji": "🎭",
  "series": "诗歌故事系列",
  "series_category": "poetry",
  "desc": "雷迪嘎嘎系列诗歌故事系列中的故事",
  "pages": 8,
  "age": "3-8岁",
  "time": 6,
  "status": "即将上线",
  "chars": [
    "雷迪嘎嘎"
  ],
  "tags": [
    "诗歌",
    "韵律"
  ],
  "text": [
    {
      "page": 1,
      "body": "雷迪嘎嘎给孩子们讲范蠡的故事。"
    },
    {
      "page": 2,
      "body": "\"'霸业休休难隐逃，泛游苕霅'。\""
    },
    {
      "page": 3,
      "body": "\"'霸业休歇难以隐藏逃避，泛游在苕霅。'\""
    },
    {
      "page": 4,
      "body": "爸爸说：\"这是曾瑞写的《柳营曲·范蠡》。\""
    },
    {
      "page": 5,
      "body": "\"'一叶扁舟，万古风光'。\""
    },
    {
      "page": 6,
      "body": "\"'一叶扁舟，万古风光。'\""
    },
    {
      "page": 7,
      "body": "\"'范蠡帮助越王勾践复国后，功成身退，和西施一起隐居了。'\""
    },
    {
      "page": 8,
      "body": "\"'这首散曲赞美了范蠡的智慧和淡泊！'\"\n---\n*故事完*"
    }
  ],
  "source": "诗歌故事系列/故事文本/诗歌_149_柳营曲范蠡.md"
}