{
  "id": "诗歌故事系列-示儿-陆游",
  "title": "《示儿》- 陆游",
  "emoji": "🎭",
  "series": "诗歌故事系列",
  "series_category": "poetry",
  "desc": "雷迪嘎嘎系列诗歌故事系列中的故事",
  "pages": 16,
  "age": "3-8岁",
  "time": 6,
  "status": "即将上线",
  "chars": [
    "噶丫丫",
    "噶巴巴",
    "雷迪嘎嘎"
  ],
  "tags": [
    "诗歌",
    "韵律"
  ],
  "text": [
    {
      "page": 1,
      "body": "雷迪嘎嘎给噶巴巴和噶丫丫讲陆游的故事。"
    },
    {
      "page": 2,
      "body": "\"陆游是南宋著名的爱国诗人。\"爸爸说。"
    },
    {
      "page": 3,
      "body": "\"'死去元知万事空'，是说本来知道人死了什么都是空的。\"爸爸念道。"
    },
    {
      "page": 4,
      "body": "\"'但悲不见九州同'，是说唯一悲伤的是没能看到祖国统一。\""
    },
    {
      "page": 5,
      "body": "\"'九州'指的是全中国，'同'就是统一。\""
    },
    {
      "page": 6,
      "body": "\"'王师北定中原日'，是说等宋朝军队收复中原的那一天。\""
    },
    {
      "page": 7,
      "body": "\"'家祭无忘告乃翁'，是说祭拜时别忘了告诉我。\""
    },
    {
      "page": 8,
      "body": "爸爸说：\"这是宋代诗人陆游写的《示儿》，是他临终前写给儿子的诗。\""
    },
    {
      "page": 9,
      "body": "\"'陆游虽然要死了，但他最牵挂的还是祖国能不能统一。\""
    },
    {
      "page": 10,
      "body": "\"'这种爱国精神，直到死都没有改变。\""
    },
    {
      "page": 11,
      "body": "噶巴巴感动地说：\"陆游爸爸真伟大！\""
    },
    {
      "page": 12,
      "body": "\"'示儿'就是写给儿子的诗。\""
    },
    {
      "page": 13,
      "body": "三只乌鸦被陆游的爱国精神深深感动。"
    },
    {
      "page": 14,
      "body": "\"示儿——陆游\"爸爸说，\"这是一首表达爱国情怀的千古名篇。\""
    },
    {
      "page": 15,
      "body": "爸爸说：\"爱国是中华民族的传统美德，我们要永远热爱祖国！\""
    },
    {
      "page": 16,
      "body": "森林上空飘扬的旗帜，在阳光下闪闪发光。\n---\n*故事完*"
    }
  ],
  "source": "诗歌故事系列/故事文本/诗歌_037_示儿.md"
}